MANIFEST.in
README.rst
setup.py
docs/HISTORY.txt
docs/LICENSE.GPL
docs/LICENSE.txt
ftw/__init__.py
ftw.addressblock.egg-info/PKG-INFO
ftw.addressblock.egg-info/SOURCES.txt
ftw.addressblock.egg-info/dependency_links.txt
ftw.addressblock.egg-info/entry_points.txt
ftw.addressblock.egg-info/namespace_packages.txt
ftw.addressblock.egg-info/not-zip-safe
ftw.addressblock.egg-info/requires.txt
ftw.addressblock.egg-info/top_level.txt
ftw/addressblock/__init__.py
ftw/addressblock/configure.zcml
ftw/addressblock/hooks.py
ftw/addressblock/interfaces.py
ftw/addressblock/lawgiver.zcml
ftw/addressblock/permissions.zcml
ftw/addressblock/resources.zcml
ftw/addressblock/testing.py
ftw/addressblock/Extensions/__init__.py
ftw/addressblock/Extensions/install.py
ftw/addressblock/behaviors/__init__.py
ftw/addressblock/behaviors/communication.py
ftw/addressblock/behaviors/configure.zcml
ftw/addressblock/behaviors/default.py
ftw/addressblock/behaviors/department.py
ftw/addressblock/behaviors/misc.py
ftw/addressblock/browser/__init__.py
ftw/addressblock/browser/configure.zcml
ftw/addressblock/browser/views.py
ftw/addressblock/browser/resources/addressblock.scss
ftw/addressblock/browser/templates/address.pt
ftw/addressblock/browser/templates/block.pt
ftw/addressblock/browser/templates/detail.pt
ftw/addressblock/contact/__init__.py
ftw/addressblock/contact/configure.zcml
ftw/addressblock/contact/interfaces.py
ftw/addressblock/contact/browser/__init__.py
ftw/addressblock/contact/browser/configure.zcml
ftw/addressblock/contact/browser/contact.py
ftw/addressblock/contact/profiles/default/browserlayer.xml
ftw/addressblock/contact/profiles/default/metadata.xml
ftw/addressblock/contact/skins/ftw.addressblock.contact/contact-info.py
ftw/addressblock/content/__init__.py
ftw/addressblock/content/addressblock.py
ftw/addressblock/geo/__init__.py
ftw/addressblock/geo/adapters.py
ftw/addressblock/geo/behaviours.py
ftw/addressblock/geo/configure.zcml
ftw/addressblock/geo/Extensions/__init__.py
ftw/addressblock/geo/Extensions/install.py
ftw/addressblock/geo/profiles/default/metadata.xml
ftw/addressblock/geo/profiles/default/registry.xml
ftw/addressblock/geo/profiles/default/types/ftw.addressblock.AddressBlock.xml
ftw/addressblock/geo/profiles/uninstall/registry.xml
